aws_amplify/cdk/exported_backend/__init__.py
aws_amplify/cdk/exported_backend/py.typed
aws_amplify/cdk/exported_backend/_jsii/__init__.py
aws_amplify/cdk/exported_backend/_jsii/cdk-exported-backend@0.0.6.jsii.tgz
aws_amplify.cdk.exported_backend-0.0.6.dist-info/LICENSE
aws_amplify.cdk.exported_backend-0.0.6.dist-info/METADATA
aws_amplify.cdk.exported_backend-0.0.6.dist-info/NOTICE
aws_amplify.cdk.exported_backend-0.0.6.dist-info/WHEEL
aws_amplify.cdk.exported_backend-0.0.6.dist-info/top_level.txt
aws_amplify.cdk.exported_backend-0.0.6.dist-info/RECORD
