Metadata-Version: 2.1
Name: aws-amplify.cdk.exported-backend
Version: 0.0.6
Summary: @aws-amplify/cdk-exported-backend
Home-page: https://github.com/aws-amplify/amplify-cli-export-construct.git
Author: Amazon Web Services<amplify-cli@amazon.com>
License: Apache-2.0
Project-URL: Source, https://github.com/aws-amplify/amplify-cli-export-construct.git
Platform: UNKNOWN
Classifier: Intended Audience :: Developers
Classifier: Operating System :: OS Independent
Classifier: Programming Language :: JavaScript
Classifier: Programming Language :: Python :: 3 :: Only
Classifier: Programming Language :: Python :: 3.7
Classifier: Programming Language :: Python :: 3.8
Classifier: Programming Language :: Python :: 3.9
Classifier: Programming Language :: Python :: 3.10
Classifier: Typing :: Typed
Classifier: Development Status :: 5 - Production/Stable
Classifier: License :: OSI Approved
Requires-Python: ~=3.7
License-File: LICENSE
License-File: NOTICE
Requires-Dist: aws-cdk-lib (<3.0.0,>=2.47.0)
Requires-Dist: constructs (<11.0.0,>=10.1.139)
Requires-Dist: jsii (<2.0.0,>=1.70.0)
Requires-Dist: publication (>=0.0.3)
Requires-Dist: typeguard (~=2.13.3)
